py3qterm/__init__.py
py3qterm/backend.py
py3qterm/demo.py
py3qterm/frontend.py
py3qterm/procinfo.py
py3qterm/test.py
py3qterm-0.4.dist-info/LICENSE
py3qterm-0.4.dist-info/METADATA
py3qterm-0.4.dist-info/WHEEL
py3qterm-0.4.dist-info/top_level.txt
py3qterm-0.4.dist-info/RECORD
